pietunes/__init__.py
pietunes/__version__.py
pietunes/api.py
pietunes/core.py
pietunes/enums.py
pietunes/script_support.py
pietunes-0.0.5.dist-info/LICENSE
pietunes-0.0.5.dist-info/METADATA
pietunes-0.0.5.dist-info/WHEEL
pietunes-0.0.5.dist-info/top_level.txt
pietunes-0.0.5.dist-info/RECORD
