Metadata-Version: 2.1
Name: pietunes
Version: 0.0.5
Summary: A library to aid in automating iTunes via ScriptingBridge.
Home-page: https://pypi.org/project/pietunes/
Author: Brian Farrell
Author-email: brian.farrell@me.com
License: AGPLv3
Keywords: modern development iTunes ScriptingBridge osx darwin
Platform: UNKNOWN
Classifier: Development Status :: 2 - Pre-Alpha
Classifier: Intended Audience :: Developers
Classifier: License :: OSI Approved :: GNU Affero General Public License v3
Classifier: License :: OSI Approved :: GNU Affero General Public License v3 or later (AGPLv3+)
Classifier: Topic :: Multimedia :: Sound/Audio
Classifier: Topic :: Multimedia :: Video
Classifier: Topic :: Software Development :: Libraries
Classifier: Environment :: Console
Classifier: Operating System :: MacOS
Classifier: Operating System :: MacOS :: MacOS X
Classifier: Programming Language :: Python
Classifier: Programming Language :: Python :: 3
Classifier: Programming Language :: Python :: 3.6
Classifier: Programming Language :: Python :: 3.7
Classifier: Programming Language :: Python :: Implementation :: CPython
Requires-Python: >=3.6.0
Requires-Dist: pyobjc-core (>=6.1)
Requires-Dist: pyobjc-framework-AppleScriptObjC (>=6.1)
Requires-Dist: pyobjc-framework-Cocoa (>=6.1)
Requires-Dist: pyobjc-framework-iTunesLibrary (>=6.1)
Requires-Dist: pyobjc-framework-Quartz (>=6.1)
Requires-Dist: pyobjc-framework-ScriptingBridge (>=6.1)
Requires-Dist: pyobjc-framework-StoreKit (>=6.1)
